{
  "parent": "minecraft:recipes/root",
  "criteria": {
    "has_meat_grinder": {
      "conditions": {
        "items": [
          {
            "items": "goldfishmod02tastyfurniture:meatgrinder"
          }
        ]
      },
      "trigger": "minecraft:inventory_changed"
    },
    "has_the_recipe": {
      "conditions": {
        "recipe": "goldfishmod02tastyfurniture:ground_cod"
      },
      "trigger": "minecraft:recipe_unlocked"
    }
  },
  "requirements": [
    [
      "has_the_recipe",
      "has_meat_grinder"
    ]
  ],
  "rewards": {
    "recipes": [
      "goldfishmod02tastyfurniture:ground_cod"
    ]
  }
}